shortgenius/__init__.py
shortgenius/_base_client.py
shortgenius/_client.py
shortgenius/_compat.py
shortgenius/_constants.py
shortgenius/_exceptions.py
shortgenius/_files.py
shortgenius/_models.py
shortgenius/_qs.py
shortgenius/_resource.py
shortgenius/_response.py
shortgenius/_streaming.py
shortgenius/_types.py
shortgenius/_version.py
shortgenius/py.typed
shortgenius/_utils/__init__.py
shortgenius/_utils/_logs.py
shortgenius/_utils/_proxy.py
shortgenius/_utils/_reflection.py
shortgenius/_utils/_resources_proxy.py
shortgenius/_utils/_streams.py
shortgenius/_utils/_sync.py
shortgenius/_utils/_transform.py
shortgenius/_utils/_typing.py
shortgenius/_utils/_utils.py
shortgenius/lib/.keep
shortgenius/resources/__init__.py
shortgenius/resources/connections.py
shortgenius/resources/credits.py
shortgenius/resources/health.py
shortgenius/resources/images.py
shortgenius/resources/series.py
shortgenius/resources/audio/__init__.py
shortgenius/resources/audio/audio.py
shortgenius/resources/audio/voices.py
shortgenius/resources/music/__init__.py
shortgenius/resources/music/genres.py
shortgenius/resources/music/music.py
shortgenius/resources/videos/__init__.py
shortgenius/resources/videos/drafts.py
shortgenius/resources/videos/videos.py
shortgenius/types/__init__.py
shortgenius/types/audio_create_speech_params.py
shortgenius/types/audio_list_audio_params.py
shortgenius/types/audio_list_audio_response.py
shortgenius/types/connection.py
shortgenius/types/connection_list_response.py
shortgenius/types/credit_list_response.py
shortgenius/types/draft_scene.py
shortgenius/types/draft_scene_param.py
shortgenius/types/health_check_response.py
shortgenius/types/image.py
shortgenius/types/image_create_params.py
shortgenius/types/image_list_params.py
shortgenius/types/image_list_response.py
shortgenius/types/image_list_styles_response.py
shortgenius/types/image_retrieve_response.py
shortgenius/types/series.py
shortgenius/types/series_create_params.py
shortgenius/types/series_list_params.py
shortgenius-1.0.0.dist-info/METADATA
shortgenius-1.0.0.dist-info/WHEEL
shortgenius-1.0.0.dist-info/licenses/LICENSE
shortgenius-1.0.0.dist-info/RECORD
